README
setup.cfg
setup.py
django_navigation.egg-info/PKG-INFO
django_navigation.egg-info/SOURCES.txt
django_navigation.egg-info/dependency_links.txt
django_navigation.egg-info/requires.txt
django_navigation.egg-info/top_level.txt
navigation/__init__.py
navigation/decorators.py
navigation/helpers.py
navigation/resolvers.py
navigation/templatetags/__init__.py
navigation/templatetags/navigation_tags.py