Metadata-Version: 1.0
Name: django-navigation
Version: 0.6.3
Summary: A breadcrumbs navigation application for Django framework.
Home-page: http://bitbucket.org/neithere/django-navigation/
Author: Andy Mikhailenko
Author-email: andy@neithere.net
License: GNU Lesser General Public License (LGPL), Version 3
Download-URL: http://bitbucket.org/neithere/django-navigation/src/
Keywords: django breadcrumbs navigation
Platform: UNKNOWN
Classifier: Development Status :: 3 - Alpha
Classifier: Environment :: Web Environment
Classifier: Framework :: Django
Classifier: Intended Audience :: Developers
Classifier: License :: OSI Approved :: GNU Library or Lesser General Public License (LGPL)
Classifier: Programming Language :: Python
Classifier: Topic :: Software Development :: Libraries :: Python Modules
Classifier: Topic :: Software Development :: User Interfaces
Classifier: Topic :: Software Development :: Widget Sets
